galletapy/DKR.py
galletapy/MD.py
galletapy/OS.py
galletapy/__init__.py
galletapy/boys.py
galletapy/shells.py
galletapy/basis/3-21G.bas
galletapy/basis/6-311G.bas
galletapy/basis/6-31G.bas
galletapy/basis/STO-2G.bas
galletapy/basis/STO-3G.bas
galletapy/basis/STO-4G.bas
galletapy/basis/STO-5G.bas
galletapy/basis/STO-6G.bas
galletapy/basis/__init__.py
galletapy/basis/aug-cc-pV5Z.bas
galletapy/basis/aug-cc-pVDZ.bas
galletapy/basis/aug-cc-pVQZ.bas
galletapy/basis/aug-cc-pVTZ.bas
galletapy/basis/cc-pV5Z.bas
galletapy/basis/cc-pVDZ.bas
galletapy/basis/cc-pVQZ.bas
galletapy/basis/cc-pVTZ.bas
galletapy/basis/def2-QZVP.bas
galletapy/basis/def2-QZVPP.bas
galletapy/basis/def2-SVP.bas
galletapy/basis/def2-TZVP.bas
galletapy/basis/def2-TZVPP.bas
GalletaPy-0.37.dist-info/LICENSE
GalletaPy-0.37.dist-info/METADATA
GalletaPy-0.37.dist-info/WHEEL
GalletaPy-0.37.dist-info/top_level.txt
GalletaPy-0.37.dist-info/RECORD
