Metadata-Version: 2.1
Name: GalletaPy
Version: 0.37
Summary: Paquete con código para ERIs
Home-page: https://github.com/felipelewyee/galleta
Author: Juan Felipe Huan Lew Yee
Author-email: felipe.lew.yee@gmail.com
License: UNKNOWN
Platform: UNKNOWN
Classifier: Programming Language :: Python :: 3
Classifier: License :: OSI Approved :: GNU General Public License v3 (GPLv3)
Classifier: Operating System :: OS Independent
Requires-Python: >=3.6
Requires-Dist: numpy
Requires-Dist: scipy
Requires-Dist: pubchempy
